.galahad_optrove.mesonpy.libs/libgalahad_double.so
galahad/__init__.py
galahad/arc.cpython-312-x86_64-linux-gnu.so
galahad/bgo.cpython-312-x86_64-linux-gnu.so
galahad/blls.cpython-312-x86_64-linux-gnu.so
galahad/bllsb.cpython-312-x86_64-linux-gnu.so
galahad/bqp.cpython-312-x86_64-linux-gnu.so
galahad/bqpb.cpython-312-x86_64-linux-gnu.so
galahad/bsc.cpython-312-x86_64-linux-gnu.so
galahad/clls.cpython-312-x86_64-linux-gnu.so
galahad/convert.cpython-312-x86_64-linux-gnu.so
galahad/cqp.cpython-312-x86_64-linux-gnu.so
galahad/cro.cpython-312-x86_64-linux-gnu.so
galahad/dgo.cpython-312-x86_64-linux-gnu.so
galahad/dps.cpython-312-x86_64-linux-gnu.so
galahad/dqp.cpython-312-x86_64-linux-gnu.so
galahad/eqp.cpython-312-x86_64-linux-gnu.so
galahad/expo.cpython-312-x86_64-linux-gnu.so
galahad/fdc.cpython-312-x86_64-linux-gnu.so
galahad/fit.cpython-312-x86_64-linux-gnu.so
galahad/glrt.cpython-312-x86_64-linux-gnu.so
galahad/gls.cpython-312-x86_64-linux-gnu.so
galahad/gltr.cpython-312-x86_64-linux-gnu.so
galahad/hash.cpython-312-x86_64-linux-gnu.so
galahad/ir.cpython-312-x86_64-linux-gnu.so
galahad/l2rt.cpython-312-x86_64-linux-gnu.so
galahad/lhs.cpython-312-x86_64-linux-gnu.so
galahad/llsr.cpython-312-x86_64-linux-gnu.so
galahad/llst.cpython-312-x86_64-linux-gnu.so
galahad/lms.cpython-312-x86_64-linux-gnu.so
galahad/lpa.cpython-312-x86_64-linux-gnu.so
galahad/lpb.cpython-312-x86_64-linux-gnu.so
galahad/lsqp.cpython-312-x86_64-linux-gnu.so
galahad/lsrt.cpython-312-x86_64-linux-gnu.so
galahad/lstr.cpython-312-x86_64-linux-gnu.so
galahad/nls.cpython-312-x86_64-linux-gnu.so
galahad/nodend.cpython-312-x86_64-linux-gnu.so
galahad/presolve.cpython-312-x86_64-linux-gnu.so
galahad/psls.cpython-312-x86_64-linux-gnu.so
galahad/qpa.cpython-312-x86_64-linux-gnu.so
galahad/qpb.cpython-312-x86_64-linux-gnu.so
galahad/roots.cpython-312-x86_64-linux-gnu.so
galahad/rpd.cpython-312-x86_64-linux-gnu.so
galahad/rqs.cpython-312-x86_64-linux-gnu.so
galahad_optrove-5.3.0.dist-info/LICENSE
galahad_optrove-5.3.0.dist-info/METADATA
galahad_optrove-5.3.0.dist-info/WHEEL
galahad_optrove-5.3.0.dist-info/RECORD
