Metadata-Version: 2.1
Name: galahad-optrove
Version: 5.3.0
Summary: A library of modern Fortran modules for nonlinear optimization
Keywords: mathematics,optimization
Author-Email: Nick Gould <nick.gould@stfc.ac.uk>, Jaroslav Fowkes <jaroslav.fowkes@stfc.ac.uk>
Maintainer-Email: Nick Gould <nick.gould@stfc.ac.uk>, Jaroslav Fowkes <jaroslav.fowkes@stfc.ac.uk>
License: GALAHAD--- a thread-safe library of modern Fortran packages with
Classifier: Development Status :: 5 - Production/Stable
Classifier: Environment :: Console
Classifier: Framework :: IPython
Classifier: Framework :: Jupyter
Classifier: Intended Audience :: Science/Research
Classifier: License :: OSI Approved :: BSD License
Classifier: Operating System :: MacOS
Classifier: Operating System :: Unix
Classifier: Programming Language :: Python
Classifier: Programming Language :: Python :: 3
Classifier: Programming Language :: Python :: 3.10
Classifier: Programming Language :: Python :: 3.11
Classifier: Programming Language :: Python :: 3.12
Classifier: Programming Language :: Python :: 3.13
Classifier: Topic :: Scientific/Engineering
Classifier: Topic :: Scientific/Engineering :: Mathematics
Project-URL: Homepage, https://www.galahad.rl.ac.uk/
Project-URL: Download, https://github.com/ralna/galahad//releases/
Project-URL: Bug Tracker, https://github.com/ralna/galahad//issues/
Project-URL: Documentation, https://www.galahad.rl.ac.uk/
Project-URL: Source Code, https://github.com/ralna/galahad/
Requires-Python: >=3.10
Requires-Dist: numpy
